workflow_runner_sentence_transformers_client/__init__.py
workflow_runner_sentence_transformers_client/api/__init__.py
workflow_runner_sentence_transformers_client/api/default/__init__.py
workflow_runner_sentence_transformers_client/api/default/root_retrieve_get.py
workflow_runner_sentence_transformers_client/client.py
workflow_runner_sentence_transformers_client/errors.py
workflow_runner_sentence_transformers_client/models/__init__.py
workflow_runner_sentence_transformers_client/models/http_validation_error.py
workflow_runner_sentence_transformers_client/models/retriver_request.py
workflow_runner_sentence_transformers_client/models/root_retrieve_get_response_root_retrieve_get.py
workflow_runner_sentence_transformers_client/models/validation_error.py
workflow_runner_sentence_transformers_client/py.typed
workflow_runner_sentence_transformers_client/types.py
workflow_runner_sentence_transformers_client-0.1.1.dist-info/METADATA
workflow_runner_sentence_transformers_client-0.1.1.dist-info/WHEEL
workflow_runner_sentence_transformers_client-0.1.1.dist-info/RECORD
